db_weights/__init__.py
db_weights/weights.py
tests/__init__.py
tests/test_weights.py
db_weights-0.0.7.dist-info/LICENSE
db_weights-0.0.7.dist-info/METADATA
db_weights-0.0.7.dist-info/WHEEL
db_weights-0.0.7.dist-info/top_level.txt
db_weights-0.0.7.dist-info/RECORD
