Metadata-Version: 2.1
Name: db_weights
Version: 0.0.7
Summary: Calculating db_weights for test data based on training data.
Home-page: https://github.com/WeightedBasedAI/db_weights
Author: Aydin Abedinia
Author-email: abedinia.aydin@gmail.com
Classifier: Programming Language :: Python :: 3
Classifier: License :: OSI Approved :: MIT License
Classifier: Operating System :: OS Independent
Requires-Python: >=3.6
License-File: LICENSE
Requires-Dist: numpy ==2.0.0
Requires-Dist: scikit-learn ==1.5.1
Requires-Dist: scipy ==1.14.0
Requires-Dist: joblib ==1.4.2
